{
    "_links": {
        "self": {
            "href": "https:\/\/8080-jessicayir8-proyectofin-66w77pdoczi.ws-us100.gitpod.io\/node\/5?_format=hal_json"
        },
        "type": {
            "href": "https:\/\/8080-jessicayir8-proyectofin-66w77pdoczi.ws-us100.gitpod.io\/rest\/type\/node\/landing_page_video"
        },
        "https:\/\/8080-jessicayir8-proyectofin-66w77pdoczi.ws-us100.gitpod.io\/rest\/relation\/node\/landing_page_video\/revision_uid": [
            {
                "href": "https:\/\/8080-jessicayir8-proyectofin-66w77pdoczi.ws-us100.gitpod.io\/user\/0?_format=hal_json"
            }
        ],
        "https:\/\/8080-jessicayir8-proyectofin-66w77pdoczi.ws-us100.gitpod.io\/rest\/relation\/node\/landing_page_video\/uid": [
            {
                "href": "https:\/\/8080-jessicayir8-proyectofin-66w77pdoczi.ws-us100.gitpod.io\/user\/0?_format=hal_json",
                "lang": "en"
            }
        ],
        "https:\/\/8080-jessicayir8-proyectofin-66w77pdoczi.ws-us100.gitpod.io\/rest\/relation\/node\/landing_page_video\/field_video_category": [
            {
                "href": "https:\/\/8080-jessicayir8-proyectofin-66w77pdoczi.ws-us100.gitpod.io\/taxonomy\/term\/6?_format=hal_json"
            },
            {
                "href": "https:\/\/8080-jessicayir8-proyectofin-66w77pdoczi.ws-us100.gitpod.io\/taxonomy\/term\/7?_format=hal_json"
            }
        ]
    },
    "nid": [
        {
            "value": 5
        }
    ],
    "uuid": [
        {
            "value": "547d54b9-6604-426c-ae1d-6f86aff22fa8"
        }
    ],
    "langcode": [
        {
            "value": "en",
            "lang": "en"
        }
    ],
    "type": [
        {
            "target_id": "landing_page_video"
        }
    ],
    "revision_timestamp": [
        {
            "value": "2023-06-07T20:53:08+00:00",
            "format": "Y-m-d\\TH:i:sP"
        }
    ],
    "_embedded": {
        "https:\/\/8080-jessicayir8-proyectofin-66w77pdoczi.ws-us100.gitpod.io\/rest\/relation\/node\/landing_page_video\/revision_uid": [
            {
                "_links": {
                    "self": {
                        "href": "https:\/\/8080-jessicayir8-proyectofin-66w77pdoczi.ws-us100.gitpod.io\/user\/0?_format=hal_json"
                    },
                    "type": {
                        "href": "https:\/\/8080-jessicayir8-proyectofin-66w77pdoczi.ws-us100.gitpod.io\/rest\/type\/user\/user"
                    }
                },
                "uuid": [
                    {
                        "value": "1dee6eb3-99d2-406c-b960-157c9be4c738"
                    }
                ]
            }
        ],
        "https:\/\/8080-jessicayir8-proyectofin-66w77pdoczi.ws-us100.gitpod.io\/rest\/relation\/node\/landing_page_video\/uid": [
            {
                "_links": {
                    "self": {
                        "href": "https:\/\/8080-jessicayir8-proyectofin-66w77pdoczi.ws-us100.gitpod.io\/user\/0?_format=hal_json"
                    },
                    "type": {
                        "href": "https:\/\/8080-jessicayir8-proyectofin-66w77pdoczi.ws-us100.gitpod.io\/rest\/type\/user\/user"
                    }
                },
                "uuid": [
                    {
                        "value": "1dee6eb3-99d2-406c-b960-157c9be4c738"
                    }
                ],
                "lang": "en"
            }
        ],
        "https:\/\/8080-jessicayir8-proyectofin-66w77pdoczi.ws-us100.gitpod.io\/rest\/relation\/node\/landing_page_video\/field_video_category": [
            {
                "_links": {
                    "self": {
                        "href": "https:\/\/8080-jessicayir8-proyectofin-66w77pdoczi.ws-us100.gitpod.io\/taxonomy\/term\/6?_format=hal_json"
                    },
                    "type": {
                        "href": "https:\/\/8080-jessicayir8-proyectofin-66w77pdoczi.ws-us100.gitpod.io\/rest\/type\/taxonomy_term\/categoria_post"
                    }
                },
                "uuid": [
                    {
                        "value": "8588f472-abaa-4cda-bcb5-aa0d48359aa3"
                    }
                ]
            },
            {
                "_links": {
                    "self": {
                        "href": "https:\/\/8080-jessicayir8-proyectofin-66w77pdoczi.ws-us100.gitpod.io\/taxonomy\/term\/7?_format=hal_json"
                    },
                    "type": {
                        "href": "https:\/\/8080-jessicayir8-proyectofin-66w77pdoczi.ws-us100.gitpod.io\/rest\/type\/taxonomy_term\/categoria_post"
                    }
                },
                "uuid": [
                    {
                        "value": "8663fce1-cfdc-4f17-a772-8eeebb8d1059"
                    }
                ]
            }
        ]
    },
    "status": [
        {
            "value": true,
            "lang": "en"
        }
    ],
    "title": [
        {
            "value": "Landing-page-Video - Veniam",
            "lang": "en"
        }
    ],
    "created": [
        {
            "value": "2023-06-07T00:58:57+00:00",
            "lang": "en",
            "format": "Y-m-d\\TH:i:sP"
        }
    ],
    "changed": [
        {
            "value": "2023-06-07T20:53:08+00:00",
            "lang": "en",
            "format": "Y-m-d\\TH:i:sP"
        }
    ],
    "promote": [
        {
            "value": true,
            "lang": "en"
        }
    ],
    "sticky": [
        {
            "value": false,
            "lang": "en"
        }
    ],
    "default_langcode": [
        {
            "value": true,
            "lang": "en"
        }
    ],
    "revision_translation_affected": [
        {
            "value": true,
            "lang": "en"
        }
    ],
    "path": [
        {
            "alias": null,
            "pid": null,
            "langcode": "en",
            "lang": "en"
        }
    ],
    "field_video_description": [
        {
            "value": "Dolus iaceo ibidem pagus sino. Dolus duis praemitto. Consectetuer consequat elit inhibeo premo similis torqueo. Consectetuer ille iriure iustum modo nisl pertineo saepius uxor vulpes. Capto esca huic iusto ludus natu vel velit. Aliquip duis humo letalis nimis. Pecus usitas verto. Capto dignissim magna obruo occuro rusticus suscipere ullamcorper wisi.\n\nFeugiat torqueo ulciscor. Augue facilisi mauris saluto sudo ut. Decet nimis vereor. Adipiscing ex vulpes zelus. Fere nostrud pecus. Causa elit praemitto ullamcorper. Causa duis haero in laoreet meus nimis usitas vulpes. Causa gemino tum. Camur consequat meus qui refero. Augue commoveo dolor ibidem pagus tum. Cogo eros hendrerit tum ullamcorper.\n\nDolor fere luctus odio os secundum singularis. Augue capto metuo molior neo tum. Amet antehabeo erat esca eum gravis persto venio zelus. Antehabeo cui genitus melior pala quidne suscipit vicis. Esse haero huic molior saepius ut vereor. Ad decet pagus ullamcorper. Ea exerci gravis lobortis metuo mos vulputate. Cogo genitus gilvus jumentum metuo obruo quae suscipere valde.\n\nAdipiscing huic turpis. Abico amet esse eum lenis molior praesent. Aliquip defui dignissim enim venio volutpat. Humo letalis praemitto utinam velit. Damnum ea hos humo neque quidne similis. Dolore esse jus loquor lucidus pertineo quae si.\n\nIn oppeto pagus pertineo praesent velit ymo. Consectetuer gravis pecus. Ad dolor exerci genitus luctus neque patria ut wisi. Decet defui gravis hendrerit melior plaga praesent singularis. Decet eu minim odio refero refoveo tego utinam validus. Facilisis pecus verto. Hendrerit neque proprius secundum torqueo.\n\nCaecus gemino jugis luptatum plaga rusticus tamen te utrum. Consectetuer dolore minim pecus pertineo singularis. At blandit esse incassum iustum rusticus saluto. Ex ille imputo interdico. Dolore ex hendrerit magna nibh pala praesent vereor. Aliquam distineo dolore esse huic macto probo quis roto sed. Augue decet letalis.\n\nAbbas facilisi fere ibidem os quadrum suscipit tincidunt. Abluo adipiscing ille inhibeo luctus mos populus proprius sagaciter vereor. Conventio feugiat plaga probo quadrum. Conventio eros incassum luptatum populus qui tum ymo. Caecus facilisis proprius saepius sed. Nobis refoveo ymo. Bene brevitas esca ex feugiat pertineo utinam ymo.\n\nAd dolus elit fere hos iriure praesent sagaciter valde vindico. Accumsan facilisi illum quis. Esse exerci luptatum minim sed valde. Accumsan consequat fere in inhibeo jugis jumentum similis.\n\nIustum suscipit te ullamcorper. Haero ideo magna ymo. Aptent augue eligo elit pagus praemitto turpis valetudo. Exputo immitto quidne utinam voco. Abluo comis conventio nisl persto vicis voco.\n\nDolore in nimis zelus. Hendrerit iriure praesent probo ut. Abigo in iustum nutus quia roto scisco veniam. Esse ibidem ludus minim paratus. Appellatio et meus premo tation tego verto. Aliquam autem dolus eros esca immitto in mauris valetudo ymo. Jumentum olim vel veniam. At sit valde.\n\nBene huic roto. Commodo et interdico magna mauris quadrum suscipere vel. Decet macto quia quidem refoveo volutpat vulpes. Decet nulla turpis. Abbas accumsan exerci iaceo oppeto pneum quidem sino usitas vereor. Eligo esca exerci humo luptatum oppeto pneum tego vindico.\n\nCommodo consequat ea iusto minim molior qui torqueo. Abbas ideo nulla nunc quae quidne torqueo usitas utrum verto. Comis damnum dolore nisl odio tum ymo. Decet luctus mauris voco ymo. Hos interdico nulla. Accumsan commodo haero hendrerit iriure letalis lucidus natu pneum saluto. Exerci laoreet os sagaciter ullamcorper valetudo venio vicis virtus.\n\n",
            "format": "plain_text",
            "processed": "<p>Dolus iaceo ibidem pagus sino. Dolus duis praemitto. Consectetuer consequat elit inhibeo premo similis torqueo. Consectetuer ille iriure iustum modo nisl pertineo saepius uxor vulpes. Capto esca huic iusto ludus natu vel velit. Aliquip duis humo letalis nimis. Pecus usitas verto. Capto dignissim magna obruo occuro rusticus suscipere ullamcorper wisi.<\/p>\n<p>Feugiat torqueo ulciscor. Augue facilisi mauris saluto sudo ut. Decet nimis vereor. Adipiscing ex vulpes zelus. Fere nostrud pecus. Causa elit praemitto ullamcorper. Causa duis haero in laoreet meus nimis usitas vulpes. Causa gemino tum. Camur consequat meus qui refero. Augue commoveo dolor ibidem pagus tum. Cogo eros hendrerit tum ullamcorper.<\/p>\n<p>Dolor fere luctus odio os secundum singularis. Augue capto metuo molior neo tum. Amet antehabeo erat esca eum gravis persto venio zelus. Antehabeo cui genitus melior pala quidne suscipit vicis. Esse haero huic molior saepius ut vereor. Ad decet pagus ullamcorper. Ea exerci gravis lobortis metuo mos vulputate. Cogo genitus gilvus jumentum metuo obruo quae suscipere valde.<\/p>\n<p>Adipiscing huic turpis. Abico amet esse eum lenis molior praesent. Aliquip defui dignissim enim venio volutpat. Humo letalis praemitto utinam velit. Damnum ea hos humo neque quidne similis. Dolore esse jus loquor lucidus pertineo quae si.<\/p>\n<p>In oppeto pagus pertineo praesent velit ymo. Consectetuer gravis pecus. Ad dolor exerci genitus luctus neque patria ut wisi. Decet defui gravis hendrerit melior plaga praesent singularis. Decet eu minim odio refero refoveo tego utinam validus. Facilisis pecus verto. Hendrerit neque proprius secundum torqueo.<\/p>\n<p>Caecus gemino jugis luptatum plaga rusticus tamen te utrum. Consectetuer dolore minim pecus pertineo singularis. At blandit esse incassum iustum rusticus saluto. Ex ille imputo interdico. Dolore ex hendrerit magna nibh pala praesent vereor. Aliquam distineo dolore esse huic macto probo quis roto sed. Augue decet letalis.<\/p>\n<p>Abbas facilisi fere ibidem os quadrum suscipit tincidunt. Abluo adipiscing ille inhibeo luctus mos populus proprius sagaciter vereor. Conventio feugiat plaga probo quadrum. Conventio eros incassum luptatum populus qui tum ymo. Caecus facilisis proprius saepius sed. Nobis refoveo ymo. Bene brevitas esca ex feugiat pertineo utinam ymo.<\/p>\n<p>Ad dolus elit fere hos iriure praesent sagaciter valde vindico. Accumsan facilisi illum quis. Esse exerci luptatum minim sed valde. Accumsan consequat fere in inhibeo jugis jumentum similis.<\/p>\n<p>Iustum suscipit te ullamcorper. Haero ideo magna ymo. Aptent augue eligo elit pagus praemitto turpis valetudo. Exputo immitto quidne utinam voco. Abluo comis conventio nisl persto vicis voco.<\/p>\n<p>Dolore in nimis zelus. Hendrerit iriure praesent probo ut. Abigo in iustum nutus quia roto scisco veniam. Esse ibidem ludus minim paratus. Appellatio et meus premo tation tego verto. Aliquam autem dolus eros esca immitto in mauris valetudo ymo. Jumentum olim vel veniam. At sit valde.<\/p>\n<p>Bene huic roto. Commodo et interdico magna mauris quadrum suscipere vel. Decet macto quia quidem refoveo volutpat vulpes. Decet nulla turpis. Abbas accumsan exerci iaceo oppeto pneum quidem sino usitas vereor. Eligo esca exerci humo luptatum oppeto pneum tego vindico.<\/p>\n<p>Commodo consequat ea iusto minim molior qui torqueo. Abbas ideo nulla nunc quae quidne torqueo usitas utrum verto. Comis damnum dolore nisl odio tum ymo. Decet luctus mauris voco ymo. Hos interdico nulla. Accumsan commodo haero hendrerit iriure letalis lucidus natu pneum saluto. Exerci laoreet os sagaciter ullamcorper valetudo venio vicis virtus.<\/p>\n"
        }
    ],
    "field_video_link": [
        {
            "uri": "http:\/\/www.chustowrulopr.gov",
            "title": "",
            "options": []
        }
    ]
}