{
    "_links": {
        "self": {
            "href": "https:\/\/8080-jessicayir8-proyectofin-66w77pdoczi.ws-us100.gitpod.io\/block\/3?_format=hal_json"
        },
        "type": {
            "href": "https:\/\/8080-jessicayir8-proyectofin-66w77pdoczi.ws-us100.gitpod.io\/rest\/type\/block_content\/basic"
        }
    },
    "id": [
        {
            "value": 3
        }
    ],
    "uuid": [
        {
            "value": "4a249840-028a-4fe4-ab0f-d05aca3ac805"
        }
    ],
    "langcode": [
        {
            "value": "en",
            "lang": "en"
        }
    ],
    "type": [
        {
            "target_id": "basic"
        }
    ],
    "revision_created": [
        {
            "value": "2023-06-17T21:18:34+00:00",
            "format": "Y-m-d\\TH:i:sP"
        }
    ],
    "status": [
        {
            "value": true,
            "lang": "en"
        }
    ],
    "info": [
        {
            "value": "block-for-home",
            "lang": "en"
        }
    ],
    "changed": [
        {
            "value": "2023-06-17T21:18:34+00:00",
            "lang": "en",
            "format": "Y-m-d\\TH:i:sP"
        }
    ],
    "reusable": [
        {
            "value": true
        }
    ],
    "default_langcode": [
        {
            "value": true,
            "lang": "en"
        }
    ],
    "revision_translation_affected": [
        {
            "value": true,
            "lang": "en"
        }
    ]
}